flask_sustainable/__init__.py
flask_sustainable/base.py
flask_sustainable/compress.py
flask_sustainable/extension.py
flask_sustainable/indicator.py
flask_sustainable/py.typed
flask_sustainable/score.py
flask_sustainable-0.0.3.dist-info/LICENSE
flask_sustainable-0.0.3.dist-info/WHEEL
flask_sustainable-0.0.3.dist-info/METADATA
flask_sustainable-0.0.3.dist-info/RECORD
