Metadata-Version: 2.1
Name: flask-sustainable
Version: 0.0.3
Summary: Brings sustainability to Flask via HTTP headers
Author-email: Avi Mimoun <_@avim.eu>
Requires-Python: >=3.6
Classifier: License :: OSI Approved :: MIT License
Classifier: Programming Language :: Python :: 3.6
Classifier: Programming Language :: Python :: 3.7
Classifier: Programming Language :: Python :: 3.8
Classifier: Programming Language :: Python :: 3.9
Classifier: Programming Language :: Python :: 3.10
Classifier: Framework :: Flask
Classifier: Framework :: Pytest
Classifier: Framework :: Sphinx
Requires-Dist: flask >= 2.0.0
Requires-Dist: codecarbon >= 2.1.3
Requires-Dist: brotli >= 1.0.0
Requires-Dist: zstandard >= 0.18.0
Requires-Dist: pytest >= 2.7.3 ; extra == "test"
Requires-Dist: coverage >= 6.4.2 ; extra == "test"
Requires-Dist: black >= 22.6.0 ; extra == "test"
Requires-Dist: isort >= 5.10.1 ; extra == "test"
Requires-Dist: docformatter >= 1.4 ; extra == "test"
Project-URL: Home, https://flask-sustainable.readthedocs.io/
Project-URL: Source, https://github.com/av1m/flask-sustainable.git
Provides-Extra: test
